chaosplt_experiment/__init__.py
chaosplt_experiment/__main__.py
chaosplt_experiment/auth.py
chaosplt_experiment/cache.py
chaosplt_experiment/cli.py
chaosplt_experiment/log.py
chaosplt_experiment/logging.json
chaosplt_experiment/model.py
chaosplt_experiment/schemas.py
chaosplt_experiment/server.py
chaosplt_experiment/settings.py
chaosplt_experiment/service/__init__.py
chaosplt_experiment/storage/__init__.py
chaosplt_experiment/storage/concrete.py
chaosplt_experiment/storage/interface.py
chaosplt_experiment/storage/model/__init__.py
chaosplt_experiment/storage/model/discovery.py
chaosplt_experiment/storage/model/execution.py
chaosplt_experiment/storage/model/experiment.py
chaosplt_experiment/storage/model/init.py
chaosplt_experiment/storage/model/recommendation.py
chaosplt_experiment/views/__init__.py
chaosplt_experiment/views/api/__init__.py
chaosplt_experiment/views/api/execution.py
chaosplt_experiment/views/api/experiment.py
chaosplt_experiment/views/web/__init__.py
chaosplatform_experiment-0.2.0.dist-info/LICENSE
chaosplatform_experiment-0.2.0.dist-info/METADATA
chaosplatform_experiment-0.2.0.dist-info/WHEEL
chaosplatform_experiment-0.2.0.dist-info/entry_points.txt
chaosplatform_experiment-0.2.0.dist-info/top_level.txt
chaosplatform_experiment-0.2.0.dist-info/RECORD
